{"id":"17122073","auth_type":"HH","account_source":328017,"updated":"2020-07-01T16:15:27+03:00","created":"2020-07-01T16:15:27+03:00","files":[],"source_url":null,"foreign":"1101f2d40006e527c7000133e1377864493763","key":"06e527c7","portfolio":[],"data":{"body":null,"area":{"id":"2","name":"Санкт-Петербург","url":null}},"resume":{"personal_info":{"photo":null,"first_name":"Роман","middle_name":null,"last_name":"Кузнецов","birth_date":null,"text_block":null},"source_url":null,"position":"Frontend Developer","specialization":[{"id":"1.221","name":"Программирование, Разработка","external_id":"1.221","profarea_id":"1","external_profarea_id":"1","prefarea_name":null}],"skill_set":["HTML/CSS","TypeScript","Vue + экосистема","React + экосистема, React hooks","Node.js","WebSocket, Socket.io","GraphQL","MongoDB","Git","JavaScript"],"gender":null,"experience":[{"position":"Frontend-разработчик","date_from":{"year":2019,"month":3,"day":1,"precision":2},"date_to":{"year":2019,"month":6,"day":1,"precision":2},"company":"Bart.sk","experience_area":null,"industries":null,"description":"React, Storybook, Swagger документация.\nРазработка корпоративного CRM, доработки, фичи, новые разделы сайта.","skills":null},{"position":"Frontend-разработчик","date_from":{"year":2018,"month":1,"day":1,"precision":2},"date_to":{"year":2019,"month":2,"day":1,"precision":2},"company":"Продуктовая IT компания (web, mobile)","experience_area":null,"industries":null,"description":"HTML/CSS, JS, WordPress.\nЛендинги, многостраничные сайты, не большие правки по верстке в других проектах.","skills":null}],"education":null,"contact":null,"area":{"country":null,"city":{"id":null,"name":"Санкт-Петербург","external_id":"2"},"metro":null,"address":null,"lat":0.0,"lng":0.0},"relocation":{"id":null,"name":null,"external_id":null},"citizenship":[{"id":null,"name":"Украина","external_id":"5"}],"language":null,"wanted_salary":{"amount":90000,"currency":"RUR"},"work_schedule":[{"id":null,"name":"Полный день","external_id":"fullDay"},{"id":null,"name":"Полная занятость","external_id":"full"}],"has_vehicle":false,"driver_license_types":null,"military":null,"social_ratings":null,"photos":null,"additionals":null,"wanted_place_of_work":null,"updated_on_source":"0001-01-01T00:00:00","travel_time":null}}