{"id":"40141725","auth_type":"HH","account_source":328017,"updated":"2023-10-12T13:31:08+03:00","created":"2023-10-12T13:31:08+03:00","files":[],"source_url":"https://spb.hh.ru/resume/f513f009000b54b9ff000133e1535436475049?query=%D0%BC%D0%B5%D0%BD%D0%B5%D0%B4%D0%B6%D0%B5%D1%80+%D0%BF%D0%BE+%D0%BF%D0%BE%D0%B4%D0%B1%D0%BE%D1%80%D1%83+%D0%BF%D0%B5%D1%80%D1%81%D0%BE%D0%BD%D0%B0%D0%BB%D0%B0&requestId=1697105526978960df950200b286598b&hhtmFrom=resume_search_result","foreign":"f513f009000b54b9ff000133e1535436475049","key":"0b54b9ff","portfolio":[],"data":{"body":null,"area":{"id":"2","name":"Санкт-Петербург","url":"https://api.hh.ru/areas/2"}},"resume":{"personal_info":{"photo":{"small":null,"medium":"https://store.huntflow.ru/uploads3/3/4/e/34e4566bbe30e3a939a1509529137d50.jpeg","large":null,"external_id":null,"description":null,"source":null,"id":null},"first_name":null,"middle_name":null,"last_name":null,"birth_date":{"year":2004,"month":7,"day":23,"precision":2},"text_block":{"header":null,"body":"header"}},"source_url":null,"position":"Ассистент рекрутера","specialization":null,"skill_set":["Вежливость","Дружелюбность","Организованность","Понимание поставленных задач","Рассудительность","Собранность","Поиск информации в интернет","Работа с большим объемом информации","умение работать в команде","Внимательность"],"gender":{"id":null,"name":"Женский","external_id":"female"},"experience":[{"position":"Помощник специалиста","date_from":{"year":2018,"month":6,"day":1,"precision":2},"date_to":{"year":2018,"month":7,"day":1,"precision":2},"company":"Помощник специалиста МКУ \"Молодежный центр \"Самарский\" г.о. Самара.","experience_area":null,"industries":null,"description":"- обработка входящей корреспонденции\n- работа с базой данных клиентов\n- осуществление работ по благоустройству территории","skills":null}],"education":{"level":{"id":null,"name":"Неоконченное высшее","external_id":"unfinished_higher"},"higher":[{"name":"Санкт-Петербургский государственный технологический институт (технический университет), Санкт-Петербург","description":"Управление персоналом (менеджер)","date_from":null,"date_to":{"year":2028,"month":0,"day":0,"precision":0},"education_area":null,"faculty":"управления","form":null}],"vocational":null,"elementary":null,"additional":null,"attestation":null,"certificate":null},"contact":null,"area":{"country":null,"city":{"id":null,"name":"Санкт-Петербург","external_id":"2"},"metro":{"id":null,"name":"Сенная площадь","external_id":"15.218"},"address":null,"lat":59.927135,"lng":30.320316},"relocation":{"id":null,"name":null,"external_id":null},"citizenship":[{"id":null,"name":"Россия","external_id":"113"}],"language":[{"id":"rus","name":"Русский","level":{"id":null,"name":"Родной","external_id":"l1"}}],"wanted_salary":{"amount":50000,"currency":"RUR"},"work_schedule":[{"id":null,"name":"Полный день","external_id":"fullDay"},{"id":null,"name":"Гибкий график","external_id":"flexible"},{"id":null,"name":"Удаленная работа","external_id":"remote"},{"id":null,"name":"Полная занятость","external_id":"full"},{"id":null,"name":"Частичная занятость","external_id":"part"},{"id":null,"name":"Стажировка","external_id":"probation"}],"has_vehicle":false,"driver_license_types":null,"military":null,"social_ratings":null,"photos":[{"url":"https://hhcdn.ru/photo/724340616.jpeg?t=1697192118&h=wVwGo2H5VXJR9x-WlSSuJQ","original":"https://hhcdn.ru/photo/724340616.jpeg"}],"additionals":null,"wanted_place_of_work":null,"updated_on_source":"0001-01-01T00:00:00","travel_time":{"id":null,"name":"Не имеет значения","external_id":"any"}}}