{"id":"46706716","auth_type":"HH","account_source":328017,"updated":"2024-03-25T19:47:05+03:00","created":"2024-03-25T19:47:05+03:00","files":[],"source_url":"https://spb.hh.ru/resume/1169e4b20007353dca000133e1494348584d59?utm_source=email&utm_medium=email&utm_campaign=SuitableResumesMailing&utm_content=text&sent_date=2024_03_22&email_hash=1819b83800fb4336b2005e6659f74440&contactsOpened=true","foreign":"1169e4b20007353dca000133e1494348584d59","key":"07353dca","portfolio":[],"data":{"body":null,"area":{"id":"2","name":"Санкт-Петербург","url":"https://api.hh.ru/areas/2"}},"resume":{"personal_info":{"photo":{"small":null,"medium":"https://store.huntflow.ru/uploads3/6/f/1/6f1447c77c776629a8ab03cfd23d64f0.jpeg","large":null,"external_id":null,"description":null,"source":null,"id":null},"first_name":"Владимир","middle_name":"Александрович","last_name":"Петров","birth_date":{"year":1997,"month":12,"day":17,"precision":2},"text_block":{"header":null,"body":"header"}},"source_url":null,"position":"Монтажник РЭА и приборов","specialization":null,"skill_set":["Smd монтаж","Поверхностный монтаж","Чтение схем и чертежей","Сборка ПК","Монтаж оборудования","Работа на линии"],"gender":{"id":null,"name":"Мужской","external_id":"male"},"experience":[{"position":"Слесарь-электромонтажник","date_from":{"year":2020,"month":1,"day":1,"precision":2},"date_to":{"year":2020,"month":2,"day":1,"precision":2},"company":"OOO OTIS лифт","experience_area":null,"industries":null,"description":"Работа на линии \nмонтаж и демонтаж комплектующих\nподготовка рэа к установке","skills":null},{"position":"Сборщик радиоэлектронной аппаратуры","date_from":{"year":2018,"month":9,"day":1,"precision":2},"date_to":{"year":2019,"month":6,"day":1,"precision":2},"company":"ООО БЭТ (Балтийские электронные технологии) ","experience_area":null,"industries":null,"description":"сборка катушек индуктивности\nнанесение этикеток и лака \nнамотка катушек индуктивности \nоборачивание \nмонтаж","skills":null}],"education":{"level":{"id":null,"name":"Среднее специальное","external_id":"special_secondary"},"higher":[{"name":"Колледж Красносельский","description":"Радиомеханик","date_from":null,"date_to":{"year":2019,"month":0,"day":0,"precision":0},"education_area":null,"faculty":"Радиомеханик по ремонту радиоэлектронного оборудования 4 разряда,  Радиомонтер приемных телевизионных антен 3 разряда","form":null},{"name":"Колледж судостроения и прикладных технологий","description":"Станочник широкого профиля","date_from":null,"date_to":{"year":2015,"month":0,"day":0,"precision":0},"education_area":null,"faculty":"Станочник широкого профиля","form":null}],"vocational":null,"elementary":null,"additional":null,"attestation":null,"certificate":null},"contact":[{"type":{"id":null,"name":"Мобильный телефон","external_id":"cell"},"value":"+7 911 1757650","preferred":false,"full_value":null},{"type":{"id":null,"name":"Эл. почта","external_id":"email"},"value":"vova.vovapetrov2013@yandex.ru","preferred":true,"full_value":null}],"area":{"country":null,"city":{"id":null,"name":"Санкт-Петербург","external_id":"2"},"metro":{"id":null,"name":"Ленинский проспект","external_id":"14.207"},"address":null,"lat":59.85117,"lng":30.268274},"relocation":{"id":null,"name":null,"external_id":null},"citizenship":[{"id":null,"name":"Россия","external_id":"113"}],"language":[{"id":"rus","name":"Русский","level":{"id":null,"name":"Родной","external_id":"l1"}}],"wanted_salary":null,"work_schedule":[{"id":null,"name":"Полный день","external_id":"fullDay"},{"id":null,"name":"Сменный график","external_id":"shift"},{"id":null,"name":"Гибкий график","external_id":"flexible"},{"id":null,"name":"Полная занятость","external_id":"full"}],"has_vehicle":false,"driver_license_types":null,"military":null,"social_ratings":null,"photos":[{"url":"https://img.hhcdn.ru/photo/749578091.jpeg?t=1711471394&h=boCnue8ZK9joGxSNhR7E5Q","original":"https://img.hhcdn.ru/photo/749578091.jpeg"}],"additionals":null,"wanted_place_of_work":null,"updated_on_source":"0001-01-01T00:00:00","travel_time":{"id":null,"name":"Не имеет значения","external_id":"any"}}}