{"id":"19712251","auth_type":"HH","account_source":328018,"updated":"2021-11-29T11:51:31+03:00","created":"2021-11-29T11:51:31+03:00","files":[],"source_url":"https://spb.hh.ru/resume/0acc30e90009645c98000133e1524537466e61?vacancyId=49457706&resumeId=157572248&t=2420102464&chatId=2416345598&page=0&collection=response&hhtmFrom=employer_vacancy_responses","foreign":"0acc30e90009645c98000133e1524537466e61","key":"09645c98","portfolio":[],"data":{"body":null,"area":{"id":"2","name":"Санкт-Петербург","url":"https://api.hh.ru/areas/2"}},"resume":{"personal_info":{"photo":{"small":null,"medium":"https://store.huntflow.ru/uploads2/1/e/c/1ec8cbfb69190e6bb82e61a2d596f22c/635102069.jpeg","large":null,"external_id":null,"description":null,"source":null,"id":null},"first_name":"Максим","middle_name":"Анатольевич","last_name":"Летов","birth_date":null,"text_block":{"header":null,"body":"header"}},"source_url":null,"position":"C++ junior developer","specialization":[{"id":"15.93","name":"Информационные технологии, Интернет, Мультимедиа","external_id":"15.93","profarea_id":"15","external_profarea_id":"15","prefarea_name":null}],"skill_set":["Работа в команде","Blueprints","Git","Qt","Linux","STL","English","Деловая коммуникация","Perforce","ООП","Python","Unreal Engine 4","C++","SQL","Android","Мультипоточность"],"gender":{"id":null,"name":"Мужской","external_id":"male"},"experience":[{"position":"Менеджер коммерческого отдела","date_from":{"year":2019,"month":10,"day":1,"precision":2},"date_to":{"year":2021,"month":10,"day":1,"precision":2},"company":"X-com","experience_area":null,"industries":null,"description":"Ведение переговоров, коммерческие продажи, заключение договоров.","skills":null}],"education":{"level":{"id":null,"name":"Неоконченное высшее","external_id":"unfinished_higher"},"higher":[{"name":"Военно-космическая академия им. А.Ф. Можайского, Санкт-Петербург","description":"Информационная безопасность","date_from":null,"date_to":{"year":2019,"month":0,"day":0,"precision":0},"education_area":null,"faculty":"Факультет сбора и обработки информации","form":null}],"vocational":null,"elementary":null,"additional":[{"name":"Разработка игр на Unreal Engine 4","description":null,"date_from":null,"date_to":{"year":2022,"month":0,"day":0,"precision":0},"education_area":null,"result":null}],"attestation":null,"certificate":null},"contact":[{"type":{"id":null,"name":null,"external_id":"phone"},"value":"+7 981 9840061","preferred":false,"full_value":null},{"type":{"id":null,"name":"Эл. почта","external_id":"email"},"value":"mr.letov.maxim@gmail.com","preferred":false,"full_value":null}],"area":{"country":null,"city":{"id":null,"name":"Санкт-Петербург","external_id":"2"},"metro":null,"address":null,"lat":0.0,"lng":0.0},"relocation":{"id":null,"name":null,"external_id":null},"citizenship":[{"id":null,"name":"Россия","external_id":"113"}],"language":[{"id":"rus","name":"Русский","level":{"id":null,"name":"Родной","external_id":"l1"}},{"id":"eng","name":"Английский","level":{"id":null,"name":"B1 — Средний","external_id":"b1"}}],"wanted_salary":null,"work_schedule":[{"id":null,"name":"Полный день","external_id":"fullDay"},{"id":null,"name":"Сменный график","external_id":"shift"},{"id":null,"name":"Гибкий график","external_id":"flexible"},{"id":null,"name":"Удаленная работа","external_id":"remote"},{"id":null,"name":"Полная занятость","external_id":"full"}],"has_vehicle":false,"driver_license_types":null,"military":null,"social_ratings":null,"photos":[{"url":"https://hh.ru/photo/635102069.jpeg?t=1638257603&h=TgoKvfxsTUd36gO2Vi6o8A","original":"https://hh.ru/photo/635102069.jpeg"}],"additionals":null,"wanted_place_of_work":null,"updated_on_source":"0001-01-01T00:00:00","travel_time":{"id":null,"name":"Не имеет значения","external_id":"any"}}}